docker_pid/__init__.py
docker_pid/__main__.py
docker_pid/cli.py
docker_pid/core.py
docker_pid-0.0.3.dist-info/LICENSE.txt
docker_pid-0.0.3.dist-info/METADATA
docker_pid-0.0.3.dist-info/WHEEL
docker_pid-0.0.3.dist-info/entry_points.txt
docker_pid-0.0.3.dist-info/top_level.txt
docker_pid-0.0.3.dist-info/RECORD
