Metadata-Version: 2.1
Name: docker-pid
Version: 0.0.3
Summary: docker-pid: Listing process IDs in docker containers.
Home-page: https://github.com/masatanish/docker-pid
Author: Masata Nishida
Author-email: masatanish@gmail.com
License: MIT
Keywords: docker\
Platform: UNKNOWN
Requires-Dist: docker
Requires-Dist: click
Requires-Dist: tabulate
